moduleRS.py
example_package_by_dmytro_y-0.0.1.dist-info/licenses/LICENSE.txt
example_package_by_dmytro_y-0.0.1.dist-info/METADATA
example_package_by_dmytro_y-0.0.1.dist-info/WHEEL
example_package_by_dmytro_y-0.0.1.dist-info/top_level.txt
example_package_by_dmytro_y-0.0.1.dist-info/RECORD
