Metadata-Version: 2.4
Name: example_package_by_Dmytro_Y
Version: 0.0.1
Summary: Module for recipe scraper
Author-email: Dmytro_Y <dmitrojankivskui@gmail.com>
License: MIT License
Classifier: Programming Language :: Python :: 3
Classifier: Operating System :: OS Independent
Requires-Python: >=3.11
License-File: LICENSE.txt
Requires-Dist: requests>=2.32.3
Requires-Dist: beautifulSoup4>=4.12.3
Requires-Dist: pandas>=2.2.3
Dynamic: license-file
